LICENSE
MANIFEST.in
README.rst
setup.cfg
setup.py
codepy/__init__.py
codepy/bpl.py
codepy/cuda.py
codepy/elementwise.py
codepy/jit.py
codepy/libraries.py
codepy/toolchain.py
codepy/tools.py
codepy.egg-info/PKG-INFO
codepy.egg-info/SOURCES.txt
codepy.egg-info/dependency_links.txt
codepy.egg-info/not-zip-safe
codepy.egg-info/requires.txt
codepy.egg-info/top_level.txt
codepy/include/codepy/bpl.hpp
doc/Makefile
doc/conf.py
examples/demo.py
examples/demo_plain.py
examples/nvcc-test.py
test/test_identical_symbols.py
test/test_two_stage_compile.py