Metadata-Version: 2.1
Name: codepy
Version: 2023.1
Summary: Generate and execute native code at run time.
Home-page: http://mathema.tician.de/software/codepy
Author: Andreas Kloeckner
Author-email: inform@tiker.net
License: MIT
Classifier: Development Status :: 4 - Beta
Classifier: Intended Audience :: Developers
Classifier: Intended Audience :: Other Audience
Classifier: Intended Audience :: Science/Research
Classifier: License :: OSI Approved :: MIT License
Classifier: Natural Language :: English
Classifier: Programming Language :: Python
Classifier: Topic :: Scientific/Engineering
Classifier: Topic :: Software Development :: Libraries
Classifier: Topic :: Utilities
Requires-Python: ~=3.8
License-File: LICENSE
